{
    "Times": [
        182,
        183,
        184,
        185,
        186,
        187,
        188,
        189,
        190,
        191,
        192,
        193,
        194,
        195,
        196,
        197,
        198,
        199,
        200,
        201,
        202,
        203,
        204,
        205,
        206,
        207,
        208,
        209,
        210,
        211,
        212,
        213,
        214,
        215
    ],
    "Particles_Position": [
        [
            772.7,
            724.8
        ],
        [
            763.7,
            724.5
        ],
        null,
        null,
        null,
        null,
        [
            756.7,
            727.7
        ],
        [
            747.1,
            731.4
        ],
        [
            752.2,
            730.0
        ],
        [
            731.0,
            744.9
        ],
        null,
        [
            740.4,
            734.9
        ],
        [
            735.3,
            740.7
        ],
        [
            728.8,
            742.0
        ],
        [
            726.7,
            743.1
        ],
        [
            722.8,
            747.3
        ],
        [
            735.2,
            738.9
        ],
        [
            715.9,
            755.4
        ],
        null,
        [
            700.6,
            771.4
        ],
        [
            695.8,
            757.9
        ],
        [
            688.4,
            776.6
        ],
        [
            687.5,
            779.9
        ],
        [
            695.8,
            772.0
        ],
        [
            685.0,
            782.5
        ],
        [
            678.8,
            784.1
        ],
        [
            681.5,
            788.7
        ],
        [
            672.9,
            788.8
        ],
        [
            674.2,
            780.3
        ],
        [
            661.7,
            797.4
        ],
        [
            667.1,
            787.8
        ],
        [
            655.9,
            797.7
        ],
        [
            657.5,
            803.1
        ],
        [
            645.1,
            807.6
        ]
    ],
    "Particles_Estimated_Position": [
        [
            772.7,
            724.8
        ],
        [
            763.7,
            724.5
        ],
        [
            762.3000000000001,
            725.14
        ],
        [
            760.9000000000001,
            725.78
        ],
        [
            759.5,
            726.4200000000001
        ],
        [
            758.1,
            727.0600000000001
        ],
        [
            756.7,
            727.7
        ],
        [
            747.1,
            731.4
        ],
        [
            752.2,
            730.0
        ],
        [
            731.0,
            744.9
        ],
        [
            735.7,
            739.9
        ],
        [
            740.4,
            734.9
        ],
        [
            735.3,
            740.7
        ],
        [
            728.8,
            742.0
        ],
        [
            726.7,
            743.1
        ],
        [
            722.8,
            747.3
        ],
        [
            735.2,
            738.9
        ],
        [
            715.9,
            755.4
        ],
        [
            708.25,
            763.4
        ],
        [
            700.6,
            771.4
        ],
        [
            695.8,
            757.9
        ],
        [
            688.4,
            776.6
        ],
        [
            687.5,
            779.9
        ],
        [
            695.8,
            772.0
        ],
        [
            685.0,
            782.5
        ],
        [
            678.8,
            784.1
        ],
        [
            681.5,
            788.7
        ],
        [
            672.9,
            788.8
        ],
        [
            674.2,
            780.3
        ],
        [
            661.7,
            797.4
        ],
        [
            667.1,
            787.8
        ],
        [
            655.9,
            797.7
        ],
        [
            657.5,
            803.1
        ],
        [
            645.1,
            807.6
        ]
    ],
    "Particles_Size": [
        155,
        169,
        null,
        null,
        null,
        null,
        156,
        102,
        121,
        20,
        null,
        126,
        137,
        74,
        112,
        53,
        101,
        49,
        null,
        57,
        31,
        77,
        49,
        60,
        45,
        54,
        56,
        42,
        33,
        43,
        52,
        49,
        52,
        63
    ],
    "Particles_Bbox": [
        [
            [
                744,
                683
            ],
            [
                62,
                80
            ]
        ],
        [
            [
                733,
                682
            ],
            [
                63,
                81
            ]
        ],
        null,
        null,
        null,
        null,
        [
            [
                722,
                690
            ],
            [
                66,
                77
            ]
        ],
        [
            [
                722,
                700
            ],
            [
                50,
                66
            ]
        ],
        [
            [
                719,
                696
            ],
            [
                63,
                70
            ]
        ],
        [
            [
                729,
                743
            ],
            [
                4,
                4
            ]
        ],
        null,
        [
            [
                707,
                705
            ],
            [
                66,
                64
            ]
        ],
        [
            [
                705,
                707
            ],
            [
                63,
                66
            ]
        ],
        [
            [
                698,
                719
            ],
            [
                54,
                54
            ]
        ],
        [
            [
                700,
                717
            ],
            [
                58,
                63
            ]
        ],
        [
            [
                697,
                725
            ],
            [
                53,
                44
            ]
        ],
        [
            [
                703,
                709
            ],
            [
                65,
                55
            ]
        ],
        [
            [
                696,
                736
            ],
            [
                33,
                42
            ]
        ],
        null,
        [
            [
                670,
                742
            ],
            [
                60,
                57
            ]
        ],
        [
            [
                678,
                740
            ],
            [
                31,
                30
            ]
        ],
        [
            [
                662,
                741
            ],
            [
                55,
                63
            ]
        ],
        [
            [
                663,
                758
            ],
            [
                49,
                44
            ]
        ],
        [
            [
                666,
                745
            ],
            [
                56,
                55
            ]
        ],
        [
            [
                657,
                763
            ],
            [
                53,
                33
            ]
        ],
        [
            [
                649,
                755
            ],
            [
                52,
                49
            ]
        ],
        [
            [
                655,
                766
            ],
            [
                47,
                46
            ]
        ],
        [
            [
                649,
                768
            ],
            [
                46,
                43
            ]
        ],
        [
            [
                657,
                759
            ],
            [
                30,
                30
            ]
        ],
        [
            [
                634,
                775
            ],
            [
                50,
                52
            ]
        ],
        [
            [
                644,
                762
            ],
            [
                44,
                56
            ]
        ],
        [
            [
                634,
                772
            ],
            [
                38,
                49
            ]
        ],
        [
            [
                635,
                777
            ],
            [
                43,
                58
            ]
        ],
        [
            [
                618,
                784
            ],
            [
                54,
                48
            ]
        ]
    ],
    "Particles_Max_Intensity": [
        [
            68
        ],
        [
            69
        ],
        null,
        null,
        null,
        null,
        [
            68
        ],
        [
            68
        ],
        [
            67
        ],
        [
            48
        ],
        null,
        [
            68
        ],
        [
            68
        ],
        [
            64
        ],
        [
            63
        ],
        [
            63
        ],
        [
            69
        ],
        [
            63
        ],
        null,
        [
            60
        ],
        [
            58
        ],
        [
            60
        ],
        [
            60
        ],
        [
            59
        ],
        [
            60
        ],
        [
            59
        ],
        [
            60
        ],
        [
            59
        ],
        [
            59
        ],
        [
            59
        ],
        [
            59
        ],
        [
            60
        ],
        [
            59
        ],
        [
            59
        ]
    ],
    "Track_ID": 79,
    "classification": "non-motile",
    "probability_motility": 0.2531062864143873
}