{
    "Times": [
        231,
        232,
        233,
        234,
        235,
        236,
        237,
        238,
        239,
        240,
        241,
        242,
        243,
        244
    ],
    "Particles_Position": [
        [
            36.9,
            532.1
        ],
        [
            38.4,
            533.8
        ],
        [
            43.4,
            534.4
        ],
        [
            40.3,
            534.0
        ],
        null,
        [
            42.0,
            537.6
        ],
        [
            37.3,
            534.0
        ],
        [
            43.1,
            534.0
        ],
        [
            36.7,
            533.1
        ],
        [
            37.1,
            532.8
        ],
        [
            48.3,
            532.2
        ],
        [
            42.0,
            533.1
        ],
        [
            49.2,
            532.8
        ],
        [
            43.1,
            529.7
        ]
    ],
    "Particles_Estimated_Position": [
        [
            36.9,
            532.1
        ],
        [
            38.4,
            533.8
        ],
        [
            43.4,
            534.4
        ],
        [
            40.3,
            534.0
        ],
        [
            41.15,
            535.8
        ],
        [
            42.0,
            537.6
        ],
        [
            37.3,
            534.0
        ],
        [
            43.1,
            534.0
        ],
        [
            36.7,
            533.1
        ],
        [
            37.1,
            532.8
        ],
        [
            48.3,
            532.2
        ],
        [
            42.0,
            533.1
        ],
        [
            49.2,
            532.8
        ],
        [
            43.1,
            529.7
        ]
    ],
    "Particles_Size": [
        7,
        13,
        10,
        10,
        null,
        8,
        12,
        8,
        15,
        12,
        11,
        8,
        12,
        13
    ],
    "Particles_Bbox": [
        [
            [
                33,
                530
            ],
            [
                6,
                4
            ]
        ],
        [
            [
                36,
                532
            ],
            [
                5,
                3
            ]
        ],
        [
            [
                37,
                528
            ],
            [
                15,
                9
            ]
        ],
        [
            [
                23,
                522
            ],
            [
                29,
                20
            ]
        ],
        null,
        [
            [
                33,
                532
            ],
            [
                20,
                13
            ]
        ],
        [
            [
                26,
                527
            ],
            [
                26,
                12
            ]
        ],
        [
            [
                32,
                527
            ],
            [
                30,
                13
            ]
        ],
        [
            [
                30,
                530
            ],
            [
                10,
                6
            ]
        ],
        [
            [
                34,
                531
            ],
            [
                5,
                4
            ]
        ],
        [
            [
                35,
                527
            ],
            [
                35,
                8
            ]
        ],
        [
            [
                35,
                531
            ],
            [
                18,
                6
            ]
        ],
        [
            [
                21,
                524
            ],
            [
                47,
                25
            ]
        ],
        [
            [
                35,
                514
            ],
            [
                31,
                20
            ]
        ]
    ],
    "Particles_Max_Intensity": [
        [
            134
        ],
        [
            135
        ],
        [
            136
        ],
        [
            134
        ],
        null,
        [
            131
        ],
        [
            136
        ],
        [
            135
        ],
        [
            135
        ],
        [
            138
        ],
        [
            137
        ],
        [
            132
        ],
        [
            133
        ],
        [
            133
        ]
    ],
    "Track_ID": 156,
    "classification": "non-motile",
    "probability_motility": 0.37428444003691697
}