{
    "Times": [
        41,
        42,
        43,
        44,
        45,
        46,
        47,
        48,
        49,
        50,
        51,
        52,
        53
    ],
    "Particles_Position": [
        [
            533.1,
            357.0
        ],
        [
            533.2,
            356.7
        ],
        [
            532.1,
            345.8
        ],
        [
            536.6,
            355.8
        ],
        [
            540.9,
            347.0
        ],
        [
            551.7,
            340.9
        ],
        [
            542.4,
            341.7
        ],
        [
            558.2,
            332.8
        ],
        [
            549.0,
            323.3
        ],
        [
            553.7,
            317.0
        ],
        [
            558.9,
            318.1
        ],
        [
            565.8,
            309.3
        ],
        [
            558.5,
            319.2
        ]
    ],
    "Particles_Estimated_Position": [
        [
            533.1,
            357.0
        ],
        [
            533.2,
            356.7
        ],
        [
            532.1,
            345.8
        ],
        [
            536.6,
            355.8
        ],
        [
            540.9,
            347.0
        ],
        [
            551.7,
            340.9
        ],
        [
            542.4,
            341.7
        ],
        [
            558.2,
            332.8
        ],
        [
            549.0,
            323.3
        ],
        [
            553.7,
            317.0
        ],
        [
            558.9,
            318.1
        ],
        [
            565.8,
            309.3
        ],
        [
            558.5,
            319.2
        ]
    ],
    "Particles_Size": [
        14,
        25,
        54,
        15,
        23,
        14,
        23,
        61,
        47,
        44,
        52,
        33,
        10
    ],
    "Particles_Bbox": [
        [
            [
                514,
                343
            ],
            [
                48,
                24
            ]
        ],
        [
            [
                512,
                334
            ],
            [
                54,
                42
            ]
        ],
        [
            [
                505,
                306
            ],
            [
                51,
                70
            ]
        ],
        [
            [
                525,
                347
            ],
            [
                34,
                18
            ]
        ],
        [
            [
                527,
                333
            ],
            [
                33,
                35
            ]
        ],
        [
            [
                541,
                328
            ],
            [
                31,
                31
            ]
        ],
        [
            [
                518,
                329
            ],
            [
                46,
                32
            ]
        ],
        [
            [
                532,
                304
            ],
            [
                53,
                60
            ]
        ],
        [
            [
                510,
                299
            ],
            [
                75,
                52
            ]
        ],
        [
            [
                515,
                289
            ],
            [
                64,
                56
            ]
        ],
        [
            [
                524,
                290
            ],
            [
                59,
                58
            ]
        ],
        [
            [
                552,
                283
            ],
            [
                42,
                50
            ]
        ],
        [
            [
                551,
                304
            ],
            [
                15,
                32
            ]
        ]
    ],
    "Particles_Max_Intensity": [
        [
            112
        ],
        [
            118
        ],
        [
            119
        ],
        [
            114
        ],
        [
            117
        ],
        [
            117
        ],
        [
            118
        ],
        [
            122
        ],
        [
            123
        ],
        [
            118
        ],
        [
            115
        ],
        [
            114
        ],
        [
            119
        ]
    ],
    "Track_ID": 8,
    "classification": "non-motile",
    "probability_motility": 0.3329842344086748
}