{
    "Times": [
        28,
        29,
        30,
        31,
        32,
        33,
        34,
        35,
        36,
        37
    ],
    "Particles_Position": [
        [
            291.2,
            149.2
        ],
        [
            293.0,
            147.5
        ],
        [
            278.8,
            146.5
        ],
        [
            292.3,
            147.2
        ],
        [
            291.2,
            148.2
        ],
        [
            290.2,
            147.8
        ],
        [
            291.1,
            148.4
        ],
        [
            292.3,
            146.9
        ],
        [
            288.4,
            150.1
        ],
        [
            293.0,
            149.5
        ]
    ],
    "Particles_Estimated_Position": [
        [
            291.2,
            149.2
        ],
        [
            293.0,
            147.5
        ],
        [
            278.8,
            146.5
        ],
        [
            292.3,
            147.2
        ],
        [
            291.2,
            148.2
        ],
        [
            290.2,
            147.8
        ],
        [
            291.1,
            148.4
        ],
        [
            292.3,
            146.9
        ],
        [
            288.4,
            150.1
        ],
        [
            293.0,
            149.5
        ]
    ],
    "Particles_Size": [
        9,
        8,
        21,
        6,
        9,
        8,
        8,
        9,
        11,
        6
    ],
    "Particles_Bbox": [
        [
            [
                278,
                144
            ],
            [
                31,
                16
            ]
        ],
        [
            [
                280,
                132
            ],
            [
                29,
                28
            ]
        ],
        [
            [
                251,
                127
            ],
            [
                58,
                33
            ]
        ],
        [
            [
                287,
                143
            ],
            [
                7,
                17
            ]
        ],
        [
            [
                282,
                143
            ],
            [
                12,
                17
            ]
        ],
        [
            [
                278,
                129
            ],
            [
                23,
                31
            ]
        ],
        [
            [
                282,
                143
            ],
            [
                12,
                17
            ]
        ],
        [
            [
                287,
                143
            ],
            [
                7,
                17
            ]
        ],
        [
            [
                276,
                144
            ],
            [
                22,
                16
            ]
        ],
        [
            [
                287,
                143
            ],
            [
                11,
                17
            ]
        ]
    ],
    "Particles_Max_Intensity": [
        [
            113
        ],
        [
            113
        ],
        [
            119
        ],
        [
            113
        ],
        [
            113
        ],
        [
            114
        ],
        [
            112
        ],
        [
            114
        ],
        [
            111
        ],
        [
            111
        ]
    ],
    "Track_ID": 56,
    "classification": "non-motile",
    "probability_motility": 0.40107815997893015
}